{"name":"826d9bf5-de07-4ce4-ae92-2073dc3e3dea","id":"/providers/Microsoft.Flow/flows/826d9bf5-de07-4ce4-ae92-2073dc3e3dea","type":"Microsoft.Flow/flows","properties":{"apiId":"/providers/Microsoft.PowerApps/apis/shared_logicflows","displayName":"Supprimer maquette","definition":{"metadata":{"workflowEntityId":null,"processAdvisorMetadata":null,"flowChargedByPaygo":null,"flowclientsuspensionreason":"None","flowclientsuspensiontime":null,"flowclientsuspensionreasondetails":null,"creator":{"id":"31335198-2076-4885-a13d-a38c1a27271d","type":"User","tenantId":"e242425b-70fc-44dc-9ddf-c21e304e6c80"},"provisioningMethod":"FromDefinition","failureAlertSubscription":true,"clientLastModifiedTime":"2024-07-23T12:10:58.2036368Z","connectionKeySavedTimeKey":"2026-03-16T20:23:01.3833412Z"},"$schema":"https://schema.management.azure.com/providers/Microsoft.Logic/schemas/2016-06-01/workflowdefinition.json#","contentVersion":"1.0.0.0","parameters":{"$authentication":{"defaultValue":{},"type":"SecureObject"},"$connections":{"defaultValue":{},"type":"Object"}},"triggers":{"manual":{"metadata":{"operationMetadataId":"53dd2096-c869-4c17-ab0b-6e140c8b3d36"},"type":"Request","kind":"PowerAppV2","inputs":{"schema":{"type":"object","properties":{"number":{"title":"ID","type":"number","x-ms-dynamically-added":true,"description":"Entrez un nombre","x-ms-content-hint":"NUMBER"}},"required":["number"]}}}},"actions":{"Supprimer_l'élément":{"runAfter":{},"metadata":{"operationMetadataId":"d3ca9935-5e54-4712-831d-f057e6dd3536"},"type":"OpenApiConnection","inputs":{"parameters":{"dataset":"https://edfonline.sharepoint.com/sites/DISC-DSC-DQI-MAQUETTES","table":"e32559d8-799a-4117-9f05-a18da7086b55","id":"@triggerBody()['number']"},"host":{"apiId":"/providers/Microsoft.PowerApps/apis/shared_sharepointonline","connectionName":"shared_sharepointonline","operationId":"DeleteItem"},"authentication":{"value":"@json(decodeBase64(triggerOutputs().headers['X-MS-APIM-Tokens']))['$ConnectionKey']","type":"Raw"}}},"Répondre_à_une_instance_PowerApp_ou_à_un_flux":{"runAfter":{"Supprimer_l'élément":["Succeeded"]},"metadata":{"operationMetadataId":"36c6809b-0d23-478b-94e3-771f6f59795c"},"type":"Response","kind":"PowerApp","inputs":{"schema":{"type":"object","properties":{"résultat":{"title":"Résultat","x-ms-dynamically-added":true,"type":"string"}},"additionalProperties":{}},"statusCode":200,"body":{"résultat":"OK"}}}}},"connectionReferences":{"shared_sharepointonline":{"connectionName":"5c5d20f3323841c4846b4af54a482914","source":"Invoker","id":"/providers/Microsoft.PowerApps/apis/shared_sharepointonline","tier":"NotSpecified","apiName":"sharepointonline","isProcessSimpleApiReferenceConversionAlreadyDone":false}},"flowFailureAlertSubscribed":false,"isManaged":false}}